aiobaseclient/__init__.py
aiobaseclient/base.py
aiobaseclient/exceptions.py
aiobaseclient-0.4.31.dist-info/METADATA
aiobaseclient-0.4.31.dist-info/WHEEL
aiobaseclient-0.4.31.dist-info/RECORD
