Metadata-Version: 2.1
Name: aiobaseclient
Version: 0.4.31
Summary: 
Author: Pasha Podolsky
Author-email: ppodolsky@me.com
Requires-Python: >=3.8,<4.0
Classifier: Programming Language :: Python :: 3
Classifier: Programming Language :: Python :: 3.8
Classifier: Programming Language :: Python :: 3.9
Classifier: Programming Language :: Python :: 3.10
Classifier: Programming Language :: Python :: 3.11
Classifier: Programming Language :: Python :: 3.12
Requires-Dist: aiohttp-socks (>=0.9.0,<0.10.0)
Requires-Dist: aiohttp[speedups] (>=3.11.13,<4.0.0)
Requires-Dist: aiokit (>=1.3.9,<2.0.0)
Requires-Dist: izihawa-loglib (>=1.1.21,<2.0.0)
Requires-Dist: izihawa-utils (>=1.2.3,<2.0.0)
Requires-Dist: multidict (>=6.1.0,<7.0.0)
Requires-Dist: orjson (>=3.10.15,<4.0.0)
Requires-Dist: python-socks (>=2.5.3,<3.0.0)
Requires-Dist: tenacity (>=9.0.0,<9.1.0)
